jaiqu/__init__.py
jaiqu/cli.py
jaiqu/helpers.py
jaiqu/jaiqu.py
jaiqu/tests/__init__.py
jaiqu-0.0.6.dist-info/LICENSE
jaiqu-0.0.6.dist-info/METADATA
jaiqu-0.0.6.dist-info/WHEEL
jaiqu-0.0.6.dist-info/entry_points.txt
jaiqu-0.0.6.dist-info/top_level.txt
jaiqu-0.0.6.dist-info/RECORD
