Metadata-Version: 2.2
Name: jaiqu
Version: 0.0.6
Summary: AI utility to extract data from any JSON and reformat it into a new JSON with repeatable queries.
Author-email: Alex Reibman <areibman@gmail.com>, Howard Gil <howardbgil@gmail.com>, Braelyn Boynton <bboynton97@gmail.com>
Project-URL: Homepage, https://github.com/AgentOps-AI/Jaiqu
Project-URL: Issues, https://github.com/AgentOps-AI/Jaiqu/issues
Classifier: Programming Language :: Python :: 3
Classifier: License :: OSI Approved :: MIT License
Classifier: Operating System :: OS Independent
Requires-Python: >=3.7
License-File: LICENSE
Requires-Dist: jq==1.6.0
Requires-Dist: openai>=1.63.2
Requires-Dist: jsonschema==4.21.1
Requires-Dist: typer==0.9.0
Provides-Extra: dev
Requires-Dist: pytest>=7.4.4; extra == "dev"
Requires-Dist: flake8>=3.1.0; extra == "dev"
Requires-Dist: coverage[toml]>=7.4.0; extra == "dev"
